circuito7/Comportamental/contadorbinario_behav.v
module contadorbinario_behav (
    input wire clk,
    input wire rst,
    output reg [3:0] q  
);

    always @(posedge clk or posedge rst) begin
        
        if (rst) begin
            q <= 4'b0000; 
        end
        else begin
            q <= q + 1;   
        end
        
    end

endmodule

circuito7/Comportamental/contadorbinario_behav_tb.v
`include "contadorbinario_behav.v"
`timescale 1ns/100ps

module contadorbinario_behav_tb;

    reg clk_tb;
    reg rst_tb;
    wire [3:0] q_tb;

    contadorbinario_behav uut (
        .clk(clk_tb),
        .rst(rst_tb),
        .q(q_tb)
    );

    initial begin
        clk_tb = 0;
        forever #5 clk_tb = ~clk_tb;
    end

    initial begin
        $dumpfile("contadorbinario_behav.vcd");
        $dumpvars(0, contadorbinario_behav_tb);
        
        $monitor("Tempo=%0t | rst=%b, clk=%b | count=%b (%d)",
                 $time, rst_tb, clk_tb, q_tb, q_tb);

        rst_tb = 1;
        #15; 

        rst_tb = 0;

        #200; 

        rst_tb = 1;
        #20;
        rst_tb = 0;
        #20;

        $finish; 
    end

endmodule

circuito7/Comportamental/contadorbinario_behav.vcd
$date
	Sat Nov 01 12:17:01 2025
$end
$version
	Icarus Verilog
$end
$timescale
	100ps
$end
$scope module contadorbinario_behav_tb $end
$var wire 4 ! q_tb [3:0] $end
$var reg 1 " clk_tb $end
$var reg 1 # rst_tb $end
$scope module uut $end
$var wire 1 " clk $end
$var wire 1 # rst $end
$var reg 4 $ q [3:0] $end
$upscope $end
$upscope $end
$enddefinitions $end
$comment Show the parameter values. $end
$dumpall
$end
#0
$dumpvars
b0 $
1#
0"
b0 !
$end
#50
1"
#100
0"
#150
b1 !
b1 $
1"
0#
#200
0"
#250
b10 !
b10 $
1"
#300
0"
#350
b11 !
b11 $
1"
#400
0"
#450
b100 !
b100 $
1"
#500
0"
#550
b101 !
b101 $
1"
#600
0"
#650
b110 !
b110 $
1"
#700
0"
#750
b111 !
b111 $
1"
#800
0"
#850
b1000 !
b1000 $
1"
#900
0"
#950
b1001 !
b1001 $
1"
#1000
0"
#1050
b1010 !
b1010 $
1"
#1100
0"
#1150
b1011 !
b1011 $
1"
#1200
0"
#1250
b1100 !
b1100 $
1"
#1300
0"
#1350
b1101 !
b1101 $
1"
#1400
0"
#1450
b1110 !
b1110 $
1"
#1500
0"
#1550
b1111 !
b1111 $
1"
#1600
0"
#1650
b0 !
b0 $
1"
#1700
0"
#1750
b1 !
b1 $
1"
#1800
0"
#1850
b10 !
b10 $
1"
#1900
0"
#1950
b11 !
b11 $
1"
#2000
0"
#2050
b100 !
b100 $
1"
#2100
0"
#2150
b0 !
b0 $
1"
1#
#2200
0"
#2250
1"
#2300
0"
#2350
b1 !
b1 $
1"
0#
#2400
0"
#2450
b10 !
b10 $
1"
#2500
0"
#2550
b11 !
b11 $
1"
