circuito4/Comportamental/demux1p4_behav.v
module demux1p4_behav (
  input data_in,      
  input [1:0] sel,    
  output reg [3:0] y
);

  always @(*) begin
    
    y = 4'b0000; 
    
    case (sel)
      2'b00: y[0] = data_in;
      2'b01: y[1] = data_in;
      2'b10: y[2] = data_in;
      2'b11: y[3] = data_in; 
    endcase
  end

endmodule

circuito4/Comportamental/demux1p4_behav_tb.v
`include "demux1p4_behav.v"
`timescale 1ns/100ps

module demux1p4_behav_tb;

  reg data_in_tb;
  reg [1:0] sel_tb;
  wire [3:0] out_tb;
  
  demux1p4_behav uut (
    .data_in(data_in_tb),
    .sel(sel_tb),
    .y(out_tb)
  );

  initial begin
    $dumpfile("demux1p4_behav.vcd");
    $dumpvars(0, demux1p4_behav_tb);

    $monitor("Tempo=%0t | data_in=%b sel=%b | y[3:0]=%b",
             $time, data_in_tb, sel_tb, out_tb);

    data_in_tb = 1;
    sel_tb = 2'b00; #10; //  = 0001
    sel_tb = 2'b01; #10; //  = 0010
    sel_tb = 2'b10; #10; //  = 0100
    sel_tb = 2'b11; #10; //  = 1000
    
    #10;

    data_in_tb = 0;
    sel_tb = 2'b00; #10; //  = 0000
    sel_tb = 2'b01; #10; //  = 0000
    sel_tb = 2'b10; #10; //  = 0000
    sel_tb = 2'b11; #10; //  = 0000
    
    #10 $finish;
  end
  
endmodule

circuito4/Comportamental/demux1p4_behav.vcd
$date
	Sat Nov 01 11:35:51 2025
$end
$version
	Icarus Verilog
$end
$timescale
	100ps
$end
$scope module demux1p4_behav_tb $end
$var wire 4 ! out_tb [3:0] $end
$var reg 1 " data_in_tb $end
$var reg 2 # sel_tb [1:0] $end
$scope module uut $end
$var wire 1 " data_in $end
$var wire 2 $ sel [1:0] $end
$var reg 4 % y [3:0] $end
$upscope $end
$upscope $end
$enddefinitions $end
$comment Show the parameter values. $end
$dumpall
$end
#0
$dumpvars
b1 %
b0 $
b0 #
1"
b1 !
$end
#100
b10 !
b10 %
b1 #
b1 $
#200
b100 !
b100 %
b10 #
b10 $
#300
b1000 !
b1000 %
b11 #
b11 $
#500
b0 !
b0 %
b0 #
b0 $
0"
#600
b1 #
b1 $
#700
b10 #
b10 $
#800
b11 #
b11 $
