circuito7/Estrutural/dff_module.v
//flip flop D based pra usar no contador binário estrutural
module dff_module (
    input wire clk,
    input wire rst,
    input wire d,
    output reg q   
);

    always @(posedge clk or posedge rst) begin
        if (rst)
            q <= 1'b0;
        else
            q <= d;
    end
endmodule

circuito7/Estrutural/contadorbinario_struct.v
`include "dff_module.v" 

module contadorbinario_struct (
    input wire clk,
    input wire rst,
    output wire [3:0] q
);


    wire [3:0] d;

    assign d = q + 1;
    

    dff_module U0_dff ( .clk(clk), .rst(rst), .d(d[0]), .q(q[0]) );
    dff_module U1_dff ( .clk(clk), .rst(rst), .d(d[1]), .q(q[1]) );
    dff_module U2_dff ( .clk(clk), .rst(rst), .d(d[2]), .q(q[2]) );
    dff_module U3_dff ( .clk(clk), .rst(rst), .d(d[3]), .q(q[3]) );

endmodule

circuito7/Estrutural/contadorbinario_struct_tb.v
`include "contadorbinario_struct.v"
`timescale 1ns/100ps

module contadorbinario_struct_tb;

    reg clk_tb;
    reg rst_tb;
    wire [3:0] q_tb;
    

    contadorbinario_struct uut (
        .clk(clk_tb),
        .rst(rst_tb),
        .q(q_tb)
    );

    initial begin
        clk_tb = 0;
        forever #5 clk_tb = ~clk_tb;
    end

    initial begin
        $dumpfile("contadorbinario_struct.vcd");
        $dumpvars(0, contadorbinario_struct_tb);
        
        $monitor("Tempo=%0t | rst=%b, clk=%b | count=%b (%d)",
                 $time, rst_tb, clk_tb, q_tb, q_tb);
        
        rst_tb = 1;
        #15; 
        rst_tb = 0;
        #200; 
        rst_tb = 1;
        #20;
        rst_tb = 0;
        #20;

        $finish; 
    end

endmodule

circuito7/Estrutural/contadorbinario_struct.vcd
$date
	Sat Nov 01 12:28:43 2025
$end
$version
	Icarus Verilog
$end
$timescale
	100ps
$end
$scope module contadorbinario_struct_tb $end
$var wire 4 ! q_tb [3:0] $end
$var reg 1 " clk_tb $end
$var reg 1 # rst_tb $end
$scope module uut $end
$var wire 1 " clk $end
$var wire 1 # rst $end
$var wire 4 $ q [3:0] $end
$var wire 4 % d [3:0] $end
$scope module U0_dff $end
$var wire 1 " clk $end
$var wire 1 & d $end
$var wire 1 # rst $end
$var reg 1 ' q $end
$upscope $end
$scope module U1_dff $end
$var wire 1 " clk $end
$var wire 1 ( d $end
$var wire 1 # rst $end
$var reg 1 ) q $end
$upscope $end
$scope module U2_dff $end
$var wire 1 " clk $end
$var wire 1 * d $end
$var wire 1 # rst $end
$var reg 1 + q $end
$upscope $end
$scope module U3_dff $end
$var wire 1 " clk $end
$var wire 1 , d $end
$var wire 1 # rst $end
$var reg 1 - q $end
$upscope $end
$upscope $end
$upscope $end
$enddefinitions $end
$comment Show the parameter values. $end
$dumpall
$end
#0
$dumpvars
0-
0,
0+
0*
0)
0(
0'
1&
b1 %
b0 $
1#
0"
b0 !
$end
#50
1"
#100
0"
#150
0&
1(
b10 %
b1 !
b1 $
1'
1"
0#
#200
0"
#250
1&
1)
b11 %
b10 !
b10 $
0'
1"
#300
0"
#350
0&
0(
1*
b100 %
b11 !
b11 $
1'
1"
#400
0"
#450
1&
1+
0)
b101 %
b100 !
b100 $
0'
1"
#500
0"
#550
0&
1(
b110 %
b101 !
b101 $
1'
1"
#600
0"
#650
1&
1)
b111 %
b110 !
b110 $
0'
1"
#700
0"
#750
0&
0(
0*
1,
b1000 %
b111 !
b111 $
1'
1"
#800
0"
#850
1&
1-
0+
0)
b1001 %
b1000 !
b1000 $
0'
1"
#900
0"
#950
0&
1(
b1010 %
b1001 !
b1001 $
1'
1"
#1000
0"
#1050
1&
1)
b1011 %
b1010 !
b1010 $
0'
1"
#1100
0"
#1150
0&
0(
1*
b1100 %
b1011 !
b1011 $
1'
1"
#1200
0"
#1250
1&
1+
0)
b1101 %
b1100 !
b1100 $
0'
1"
#1300
0"
#1350
0&
1(
b1110 %
b1101 !
b1101 $
1'
1"
#1400
0"
#1450
1&
1)
b1111 %
b1110 !
b1110 $
0'
1"
#1500
0"
#1550
0&
0(
0*
0,
b0 %
b1111 !
b1111 $
1'
1"
#1600
0"
#1650
1&
0-
0+
0)
b1 %
b0 !
b0 $
0'
1"
#1700
0"
#1750
0&
1(
b10 %
b1 !
b1 $
1'
1"
#1800
0"
#1850
1&
1)
b11 %
b10 !
b10 $
0'
1"
#1900
0"
#1950
0&
0(
1*
b100 %
b11 !
b11 $
1'
1"
#2000
0"
#2050
1&
1+
0)
b101 %
b100 !
b100 $
0'
1"
#2100
0"
#2150
0*
b1 %
b0 !
b0 $
0+
1"
1#
#2200
0"
#2250
1"
#2300
0"
#2350
0&
1(
b10 %
b1 !
b1 $
1'
1"
0#
#2400
0"
#2450
1&
1)
b11 %
b10 !
b10 $
0'
1"
#2500
0"
#2550
0&
0(
1*
b100 %
b11 !
b11 $
1'
1"
