circuito6/Estrutural/somacompleto_struct.v
module somacompleto_struct (
    input wire a,
    input wire b,
    input wire carry_in,
    output wire sum,
    output wire carry_out
);

    wire w_sum_ha1;
    wire w_carry_ha1;
    wire w_carry_ha2;  

    xor U1_xor_ha1 (w_sum_ha1, a, b);
    and U2_and_ha1 (w_carry_ha1, a, b);

    xor U3_xor_ha2 (sum, w_sum_ha1, carry_in);
    and U4_and_ha2 (w_carry_ha2, w_sum_ha1, carry_in);

    or  U5_or_cout (carry_out, w_carry_ha1, w_carry_ha2);

endmodule

circuito6/Estrutural/somacompleto_struct_tb.v
`include "somacompleto_struct.v"
`timescale 1ns/100ps

module somacompleto_struct_tb;

    reg a_tb;
    reg b_tb;
    reg cin_tb;
    wire sum_tb;
    wire cout_tb;

    somacompleto_struct uut (
        .a(a_tb),
        .b(b_tb),
        .carry_in(cin_tb),
        .sum(sum_tb),
        .carry_out(cout_tb)
    );

    initial begin
        $dumpfile("somacompleto_struct.vcd");
        $dumpvars(0, somacompleto_struct_tb);
        
        $monitor("Tempo=%0t | a=%b, b=%b, cin=%b | sum=%b, cout=%b",
                 $time, a_tb, b_tb, cin_tb, sum_tb, cout_tb);

        a_tb = 0; b_tb = 0; cin_tb = 0; #10; // sum=0, cout=0
        a_tb = 0; b_tb = 0; cin_tb = 1; #10; // sum=1, cout=0
        a_tb = 0; b_tb = 1; cin_tb = 0; #10; // sum=1, cout=0
        a_tb = 0; b_tb = 1; cin_tb = 1; #10; // sum=0, cout=1
        a_tb = 1; b_tb = 0; cin_tb = 0; #10; // sum=1, cout=0
        a_tb = 1; b_tb = 0; cin_tb = 1; #10; // sum=0, cout=1
        a_tb = 1; b_tb = 1; cin_tb = 0; #10; // sum=0, cout=1
        a_tb = 1; b_tb = 1; cin_tb = 1; #10; // sum=1, cout=1
        
        #10 $finish; 
    end

endmodule

circuito6/Estrutural/somacompleto_struct.vcd
$date
	Sat Nov 01 12:08:30 2025
$end
$version
	Icarus Verilog
$end
$timescale
	100ps
$end
$scope module somacompleto_struct_tb $end
$var wire 1 ! sum_tb $end
$var wire 1 " cout_tb $end
$var reg 1 # a_tb $end
$var reg 1 $ b_tb $end
$var reg 1 % cin_tb $end
$scope module uut $end
$var wire 1 # a $end
$var wire 1 $ b $end
$var wire 1 % carry_in $end
$var wire 1 " carry_out $end
$var wire 1 ! sum $end
$var wire 1 & w_carry_ha1 $end
$var wire 1 ' w_carry_ha2 $end
$var wire 1 ( w_sum_ha1 $end
$upscope $end
$upscope $end
$enddefinitions $end
$comment Show the parameter values. $end
$dumpall
$end
#0
$dumpvars
0(
0'
0&
0%
0$
0#
0"
0!
$end
#100
1!
1%
#200
1(
0%
1$
#300
1"
0!
1'
1%
#400
0"
1!
0'
0%
0$
1#
#500
1"
0!
1'
1%
#600
0'
0(
1&
0%
1$
#700
1!
1%
