circuito6/Comportamental/somacompleto_behav.v
module somacompleto_behav (
    input wire a,
    input wire b,
    input wire carry_in,
    output wire sum,
    output wire carry_out
);

    assign sum = a ^ b ^ carry_in;

    assign carry_out = (a & b) | (carry_in & (a ^ b));

endmodule

circuito6/Comportamental/somacompleto_behav_tb.v
`include "somacompleto_behav.v"
`timescale 1ns/100ps

module somacompleto_behav_tb;

    reg a_tb;
    reg b_tb;
    reg cin_tb;
    wire sum_tb;
    wire cout_tb;

    somacompleto_behav uut (
        .a(a_tb),
        .b(b_tb),
        .carry_in(cin_tb),
        .sum(sum_tb),
        .carry_out(cout_tb)
    );

    initial begin
        $dumpfile("somacompleto_behav.vcd");
        $dumpvars(0, somacompleto_behav_tb);
        
        $monitor("Tempo=%0t | a=%b, b=%b, cin=%b | sum=%b, cout=%b",
                 $time, a_tb, b_tb, cin_tb, sum_tb, cout_tb);

        a_tb = 0; b_tb = 0; cin_tb = 0; #10; // sum=0, cout=0
        a_tb = 0; b_tb = 0; cin_tb = 1; #10; // sum=1, cout=0
        a_tb = 0; b_tb = 1; cin_tb = 0; #10; // sum=1, cout=0
        a_tb = 0; b_tb = 1; cin_tb = 1; #10; // sum=0, cout=1
        a_tb = 1; b_tb = 0; cin_tb = 0; #10; // sum=1, cout=0
        a_tb = 1; b_tb = 0; cin_tb = 1; #10; // sum=0, cout=1
        a_tb = 1; b_tb = 1; cin_tb = 0; #10; // sum=0, cout=1
        a_tb = 1; b_tb = 1; cin_tb = 1; #10; // sum=1, cout=1
        
        #10 $finish; 
    end

endmodule

circuito6/Comportamental/somacompleto_behav.vcd
$date
	Sat Nov 01 12:02:20 2025
$end
$version
	Icarus Verilog
$end
$timescale
	100ps
$end
$scope module somacompleto_behav_tb $end
$var wire 1 ! sum_tb $end
$var wire 1 " cout_tb $end
$var reg 1 # a_tb $end
$var reg 1 $ b_tb $end
$var reg 1 % cin_tb $end
$scope module uut $end
$var wire 1 # a $end
$var wire 1 $ b $end
$var wire 1 % carry_in $end
$var wire 1 " carry_out $end
$var wire 1 ! sum $end
$upscope $end
$upscope $end
$enddefinitions $end
$comment Show the parameter values. $end
$dumpall
$end
#0
$dumpvars
0%
0$
0#
0"
0!
$end
#100
1!
1%
#200
0%
1$
#300
1"
0!
1%
#400
0"
1!
0%
0$
1#
#500
1"
0!
1%
#600
0%
1$
#700
1!
1%
