circuito4/Estrutural/demux1p4_struct.v
module demux1p4_struct(
  input data_in,      
  input [1:0] sel,    
  output [3:0] out    
);
  
  wire not_sel1, not_sel0;
  
  not U1_not (not_sel1, sel[1]);
  not U2_not (not_sel0, sel[0]); 
  and U3_and0 (out[0], data_in, not_sel1, not_sel0);
  and U4_and1 (out[1], data_in, not_sel1, sel[0]);
  and U5_and2 (out[2], data_in, sel[1], not_sel0);
  and U6_and3 (out[3], data_in, sel[1], sel[0]);

endmodule

circuito4/Estrutural/demux1p4_struct_tb.v
`include "demux1p4_struct.v" 
`timescale 1ns/100ps

module demux1p4_struct_tb;

  reg data_in_tb;
  reg [1:0] sel_tb;
  wire [3:0] out_tb;
  
  demux1p4_struct uut (
    .data_in(data_in_tb),
    .sel(sel_tb),
    .out(out_tb)
  );
  
  initial begin
    $dumpfile("demux1p4_struct.vcd");
    $dumpvars(0, demux1p4_struct_tb);

    $monitor("Tempo=%0t | data_in=%b sel=%b | out[3:0]=%b",
             $time, data_in_tb, sel_tb, out_tb);
             
    data_in_tb = 1;
    sel_tb = 2'b00; #10; // out = 0001
    sel_tb = 2'b01; #10; // out = 0010
    sel_tb = 2'b10; #10; // out = 0100
    sel_tb = 2'b11; #10; // out = 1000
    
    #10; 
    
    data_in_tb = 0;
    sel_tb = 2'b00; #10; // out = 0000
    sel_tb = 2'b01; #10; // out = 0000
    sel_tb = 2'b10; #10; // out = 0000
    sel_tb = 2'b11; #10; // out = 0000
    
    #10 $finish;
  end
  
endmodule

circuito4/Estrutural/demux1p4_struct.vcd
$date
	Sat Nov 01 11:39:42 2025
$end
$version
	Icarus Verilog
$end
$timescale
	100ps
$end
$scope module demux1p4_struct_tb $end
$var wire 4 ! out_tb [3:0] $end
$var reg 1 " data_in_tb $end
$var reg 2 # sel_tb [1:0] $end
$scope module uut $end
$var wire 1 " data_in $end
$var wire 1 $ not_sel0 $end
$var wire 1 % not_sel1 $end
$var wire 2 & sel [1:0] $end
$var wire 4 ' out [3:0] $end
$upscope $end
$upscope $end
$enddefinitions $end
$comment Show the parameter values. $end
$dumpall
$end
#0
$dumpvars
b1 '
b0 &
1%
1$
b0 #
1"
b1 !
$end
#100
0$
b10 !
b10 '
b1 #
b1 &
#200
0%
1$
b100 !
b100 '
b10 #
b10 &
#300
0$
b1000 !
b1000 '
b11 #
b11 &
#500
1%
1$
b0 !
b0 '
b0 #
b0 &
0"
#600
0$
b1 #
b1 &
#700
0%
1$
b10 #
b10 &
#800
0$
b11 #
b11 &
