circuito8/Estrutural/subtratorcompleto_struct.v
module subtratorcompleto_struct (
    input wire a,
    input wire b,
    input wire borrow_in,
    output wire diff,
    output wire borrow_out
);

    wire w_xor1;
    wire w_a_n;
    wire w_and1;
    wire w_and2;
    wire w_and3;

    xor U1_xor (w_xor1, a, b);
    xor U2_xor (diff, w_xor1, borrow_in);

    not U3_not (w_a_n, a);
    and U4_and (w_and1, w_a_n, b);
    and U5_and (w_and2, w_a_n, borrow_in);
    and U6_and (w_and3, b, borrow_in);
    or  U7_or  (borrow_out, w_and1, w_and2, w_and3);

endmodule

circuito8/Estrutural/subtratorcompleto_struct_tb.v
`include "subtratorcompleto_struct.v"
`timescale 1ns/100ps

module subtratorcompleto_struct_tb;

    reg a_tb;
    reg b_tb;
    reg bin_tb;
    wire diff_tb;
    wire bout_tb;

    subtratorcompleto_struct uut (
        .a(a_tb),
        .b(b_tb),
        .borrow_in(bin_tb),
        .diff(diff_tb),
        .borrow_out(bout_tb)
    );

    initial begin
        $dumpfile("subtratorcompleto_struct.vcd");
        $dumpvars(0, subtratorcompleto_struct_tb);
        
        $monitor("Tempo=%0t | a=%b, b=%b, bin=%b | diff=%b, bout=%b",
                 $time, a_tb, b_tb, bin_tb, diff_tb, bout_tb);

        a_tb = 0; b_tb = 0; bin_tb = 0; #10; // diff=0, bout=0
        a_tb = 0; b_tb = 0; bin_tb = 1; #10; // diff=1, bout=1
        a_tb = 0; b_tb = 1; bin_tb = 0; #10; // diff=1, bout=1
        a_tb = 0; b_tb = 1; bin_tb = 1; #10; // diff=0, bout=1
        a_tb = 1; b_tb = 0; bin_tb = 0; #10; // diff=1, bout=0
        a_tb = 1; b_tb = 0; bin_tb = 1; #10; // diff=0, bout=0
        a_tb = 1; b_tb = 1; bin_tb = 0; #10; // diff=0, bout=0
        a_tb = 1; b_tb = 1; bin_tb = 1; #10; // diff=1, bout=1
        
        #10 $finish; 
    end

endmodule

circuito8/Estrutural/subtratorcompleto_struct.vcd
$date
	Sat Nov 01 12:37:06 2025
$end
$version
	Icarus Verilog
$end
$timescale
	100ps
$end
$scope module subtratorcompleto_struct_tb $end
$var wire 1 ! diff_tb $end
$var wire 1 " bout_tb $end
$var reg 1 # a_tb $end
$var reg 1 $ b_tb $end
$var reg 1 % bin_tb $end
$scope module uut $end
$var wire 1 # a $end
$var wire 1 $ b $end
$var wire 1 % borrow_in $end
$var wire 1 " borrow_out $end
$var wire 1 ! diff $end
$var wire 1 & w_a_n $end
$var wire 1 ' w_and1 $end
$var wire 1 ( w_and2 $end
$var wire 1 ) w_and3 $end
$var wire 1 * w_xor1 $end
$upscope $end
$upscope $end
$enddefinitions $end
$comment Show the parameter values. $end
$dumpall
$end
#0
$dumpvars
0*
0)
0(
0'
1&
0%
0$
0#
0"
0!
$end
#100
1"
1!
1(
1%
#200
0(
1*
1'
0%
1$
#300
0!
1(
1)
1%
#400
0"
1!
0(
0'
0)
0&
0%
0$
1#
#500
0!
1%
#600
0*
0%
1$
#700
1"
1!
1)
1%
